LICENSE
README.md
setup.cfg
setup.py
bin/seq-gen-version.py
bin/seq-gen.py
seqgen/__init__.py
seqgen/sequences.py
seqgen.egg-info/PKG-INFO
seqgen.egg-info/SOURCES.txt
seqgen.egg-info/dependency_links.txt
seqgen.egg-info/requires.txt
seqgen.egg-info/top_level.txt
test/test_sequences.py