Metadata-Version: 2.1
Name: seqgen
Version: 1.2.4
Summary: Command line script and Python class for generating genetic sequence data in FASTA format.
Home-page: https://github.com/acorg/seqgen
Download-URL: https://github.com/acorg/seqgen
Author: Terry Jones
Author-email: tcj25@cam.ac.uk
License: MIT
Keywords: genetic sequences
Classifier: Programming Language :: Python :: 2.7
Classifier: Programming Language :: Python :: 3.5
Classifier: Programming Language :: Python :: 3.6
Classifier: Development Status :: 4 - Beta
Classifier: Intended Audience :: Developers
Classifier: License :: OSI Approved :: MIT License
Classifier: Operating System :: OS Independent
Classifier: Topic :: Software Development :: Libraries :: Python Modules
License-File: LICENSE
Requires-Dist: dark-matter>=1.1.28
